tgtables/__init__.py
tgtables/config.py
tgtables/main.py
tgtables-0.0.1.dist-info/METADATA
tgtables-0.0.1.dist-info/WHEEL
tgtables-0.0.1.dist-info/licenses/LICENSE
tgtables-0.0.1.dist-info/RECORD
